quda/__init__.py
quda/cli.py
quda/data/__init__.py
quda/data/api.py
quda/data/tables.py
quda/data/quote/__init__.py
quda/data/quote/tick_clean.py
quda/data/update/__init__.py
quda/data/update/_jy_sql.py
quda/data/update/_mc_sql.py
quda/data/update/update_jydata.py
quda/data/update/update_mc.py
quda/data/update/update_tick.py
quda/data/zoo/__init__.py
quda/data/zoo/base.py
quda/dataset/__init__.py
quda/dataset/core.py
quda/factor/__init__.py
quda/factor/completer.py
quda/factor/consts.py
quda/factor/core.py
quda/factor/errors.py
quda/factor/evaluator.py
quda/factor/resolver.py
quda/factor/utils.py
quda/qdf/__init__.py
quda/qdf/errors.py
quda/qdf/expr.py
quda/qdf/lazy.py
quda/qdf/qdf.py
quda/qdf/udf/__init__.py
quda/qdf/udf/base_udf.py
quda/qdf/udf/cs_udf.py
quda/qdf/udf/d_udf.py
quda/qdf/udf/itd_udf.py
quda/qdf/udf/ts_udf.py
quda/updater/__init__.py
quda/updater/base.py
quda/updater/updater.py
quda-2.0.37.dist-info/METADATA
quda-2.0.37.dist-info/WHEEL
quda-2.0.37.dist-info/entry_points.txt
quda-2.0.37.dist-info/top_level.txt
quda-2.0.37.dist-info/RECORD
