Metadata-Version: 2.4
Name: quda
Version: 2.0.37
Requires-Python: >=3.12
Requires-Dist: lark>=1.2.2
Requires-Dist: rich>=14.0.0
Requires-Dist: varname>=0.14.0
Requires-Dist: typer>=0.16.0
Requires-Dist: ygo>=1.2.6
Requires-Dist: logair>=1.0.6
Requires-Dist: lidb>=1.0.9
Requires-Dist: xcals>=0.0.4
Requires-Dist: toml>=0.10.2
Requires-Dist: polars
